Workbook

Sheet README
A1: Excel Assignment: Tasks 6 to 9
A3: About the dataset
A4: Sales_Data holds 120 sample sales orders in the same column layout as the Global Superstore dataset. The original course file was not available when this workbook was built, so the sample was created for it. If the assignment requires the original file, paste its rows into Sales_Data in the same column order. Formulas on T7, T8 and T9 point to rows 2 to 121.
A6: Sheet guide
A7: Sheet | B7: Task | C7: What it contains
A8: Sales_Data | B8: 6 and 7 | C8: Formatted, sorted dataset with headers, AutoFilter and freeze panes. Conditional formatting (Task 7) is applied here.
A9: T6_Filtered_View | B9: 6 | C9: The same records with a filter applied (Region = West and Category = Technology). Non-matching rows are hidden, not deleted.
A10: T7_Cond_Format_Functions | B10: 7 | C10: Conditional formatting rules, plus IF, COUNTIF and SUMIF formulas with explanations.
A11: T8_VLOOKUP_XLOOKUP | B11: 8 | C11: VLOOKUP and XLOOKUP side by side, a reverse lookup, and a comparison table.
A12: T9_Pivot_Chart | B12: 9 | C12: Pivot-style summary built with SUMIFS, a clustered column chart and an explanation of the chart.
A13: Product_Master | B13: 8 | C13: Second related table, keyed by Product ID.
A15: Notes
A16: Yellow cells are inputs you can change.
A17: XLOOKUP needs Excel 2021, Excel 365 or Google Sheets. In older Excel versions, use the INDEX/MATCH row in T8 Part B.
A18: The workbook recalculates when it opens. If any value shows as blank, press Ctrl+Alt+F9.

Sheet Sales_Data
A1: Order ID | B1: Order Date | C1: Ship Mode | D1: Customer ID | E1: Customer Name | F1: Segment | G1: Region | H1: Product ID | I1: Category | J1: Sub-Category | K1: Sales | L1: Quantity | M1: Discount | N1: Profit | O1: Loss Flag
A2: ORD-2016-0001 | B2: 42374 | C2: Second Class | D2: CU-1001 | E2: Aarav Mehta | F2: Consumer | G2: West | H2: OFS-PA-01 | I2: Office Supplies | J2: Paper | K2: 48 | L2: 5 | M2: 0 | N2: 8.42 | O2: =IF(N2<0,"Loss","Profit")
A3: ORD-2016-0002 | B3: 42374 | C3: Second Class | D3: CU-1014 | E3: Myra Chawla | F3: Home Office | G3: West | H3: OFS-ST-02 | I3: Office Supplies | J3: Storage | K3: 103.14 | L3: 3 | M3: 0.1 | N3: 27.37 | O3: =IF(N3<0,"Loss","Profit")
A4: ORD-2016-0003 | B4: 42376 | C4: Second Class | D4: CU-1013 | E4: Aditya Pillai | F4: Consumer | G4: South | H4: TEC-MA-01 | I4: Technology | J4: Machines | K4: 2697 | L4: 5 | M4: 0.4 | N4: -267.17 | O4: =IF(N4<0,"Loss","Profit")
A5: ORD-2016-0004 | B5: 42383 | C5: First Class | D5: CU-1017 | E5: Ishaan Desai | F5: Consumer | G5: East | H5: TEC-AC-01 | I5: Technology | J5: Accessories | K5: 44.99 | L5: 1 | M5: 0 | N5: 7.44 | O5: =IF(N5<0,"Loss","Profit")
A6: ORD-2016-0005 | B6: 42384 | C6: Standard Class | D6: CU-1013 | E6: Aditya Pillai | F6: Consumer | G6: South | H6: FUR-BK-02 | I6: Furniture | J6: Bookcases | K6: 1095 | L6: 3 | M6: 0 | N6: 17.3 | O6: =IF(N6<0,"Loss","Profit")
A7: ORD-2016-0006 | B7: 42385 | C7: Same Day | D7: CU-1001 | E7: Aarav Mehta | F7: Consumer | G7: West | H7: TEC-MA-01 | I7: Technology | J7: Machines | K7: 4495 | L7: 5 | M7: 0 | N7: 635.48 | O7: =IF(N7<0,"Loss","Profit")
A8: ORD-2016-0007 | B8: 42386 | C8: Standard Class | D8: CU-1015 | E8: Ved Malhotra | F8: Consumer | G8: Central | H8: FUR-TB-01 | I8: Furniture | J8: Tables | K8: 944 | L8: 1 | M8: 0.2 | N8: -40.27 | O8: =IF(N8<0,"Loss","Profit")
A9: ORD-2016-0008 | B9: 42389 | C9: Standard Class | D9: CU-1004 | E9: Ananya Iyer | F9: Home Office | G9: South | H9: TEC-AC-01 | I9: Technology | J9: Accessories | K9: 134.97 | L9: 3 | M9: 0 | N9: 27.13 | O9: =IF(N9<0,"Loss","Profit")
A10: ORD-2016-0009 | B10: 42392 | C10: Same Day | D10: CU-1020 | E10: Navya Reddy | F10: Consumer | G10: Central | H10: TEC-AC-01 | I10: Technology | J10: Accessories | K10: 161.96 | L10: 4 | M10: 0.1 | N10: 18.27 | O10: =IF(N10<0,"Loss","Profit")
A11: ORD-2016-0010 | B11: 42395 | C11: Second Class | D11: CU-1010 | E11: Saanvi Joshi | F11: Consumer | G11: West | H11: TEC-AC-01 | I11: Technology | J11: Accessories | K11: 314.93 | L11: 7 | M11: 0 | N11: 20.71 | O11: =IF(N11<0,"Loss","Profit")
A12: ORD-2016-0011 | B12: 42403 | C12: Standard Class | D12: CU-1004 | E12: Ananya Iyer | F12: Home Office | G12: South | H12: OFS-ST-02 | I12: Office Supplies | J12: Storage | K12: 38.2 | L12: 1 | M12: 0 | N12: 9.03 | O12: =IF(N12<0,"Loss","Profit")
A13: ORD-2016-0012 | B13: 42406 | C13: Standard Class | D13: CU-1005 | E13: Kabir Singh | F13: Corporate | G13: West | H13: TEC-AC-01 | I13: Technology | J13: Accessories | K13: 26.99 | L13: 1 | M13: 0.4 | N13: -3.3 | O13: =IF(N13<0,"Loss","Profit")
... A121: ORD-2016-0120 | B121: 42731 | C121: Standard Class | D121: CU-1002 | E121: Diya Kapoor | F121: Consumer | G121: East | H121: TEC-AC-02 | I121: Technology | J121: Accessories | K121: 756 | L121: 4 | M121: 0 | N121: 74.47 | O121: =IF(N121<0,"Loss","Profit")

Sheet T6_Filtered_View
A1: Order ID | B1: Order Date | C1: Ship Mode | D1: Customer ID | E1: Customer Name | F1: Segment | G1: Region | H1: Product ID | I1: Category | J1: Sub-Category | K1: Sales | L1: Quantity | M1: Discount | N1: Profit | O1: Loss Flag | Q1: Filter applied: Region = West AND Category = Technology
A2: =Sales_Data!A2 | B2: =Sales_Data!B2 | C2: =Sales_Data!C2 | D2: =Sales_Data!D2 | E2: =Sales_Data!E2 | F2: =Sales_Data!F2 | G2: =Sales_Data!G2 | H2: =Sales_Data!H2 | ... O2: =Sales_Data!O2 | Q2: Records shown: 10 of 120 (other rows are hidden, not deleted)
A3: =Sales_Data!A3 | B3: =Sales_Data!B3 | C3: =Sales_Data!C3 | D3: =Sales_Data!D3 | E3: =Sales_Data!E3 | F3: =Sales_Data!F3 | G3: =Sales_Data!G3 | H3: =Sales_Data!H3 | ... O3: =Sales_Data!O3 | Q3: Values are linked to Sales_Data. To see all records, clear the filter on Region or Category.
A4: =Sales_Data!A4 | B4: =Sales_Data!B4 | C4: =Sales_Data!C4 | D4: =Sales_Data!D4 | E4: =Sales_Data!E4 | F4: =Sales_Data!F4 | G4: =Sales_Data!G4 | H4: =Sales_Data!H4 | ... O4: =Sales_Data!O4
A5: =Sales_Data!A5 | B5: =Sales_Data!B5 | C5: =Sales_Data!C5 | D5: =Sales_Data!D5 | E5: =Sales_Data!E5 | F5: =Sales_Data!F5 | G5: =Sales_Data!G5 | H5: =Sales_Data!H5 | ... O5: =Sales_Data!O5
A6: =Sales_Data!A6 | B6: =Sales_Data!B6 | C6: =Sales_Data!C6 | D6: =Sales_Data!D6 | E6: =Sales_Data!E6 | F6: =Sales_Data!F6 | G6: =Sales_Data!G6 | H6: =Sales_Data!H6 | ... O6: =Sales_Data!O6
A7: =Sales_Data!A7 | B7: =Sales_Data!B7 | C7: =Sales_Data!C7 | D7: =Sales_Data!D7 | E7: =Sales_Data!E7 | F7: =Sales_Data!F7 | G7: =Sales_Data!G7 | H7: =Sales_Data!H7 | ... O7: =Sales_Data!O7
A8: =Sales_Data!A8 | B8: =Sales_Data!B8 | C8: =Sales_Data!C8 | D8: =Sales_Data!D8 | E8: =Sales_Data!E8 | F8: =Sales_Data!F8 | G8: =Sales_Data!G8 | H8: =Sales_Data!H8 | ... O8: =Sales_Data!O8
A9: =Sales_Data!A9 | B9: =Sales_Data!B9 | C9: =Sales_Data!C9 | D9: =Sales_Data!D9 | E9: =Sales_Data!E9 | F9: =Sales_Data!F9 | G9: =Sales_Data!G9 | H9: =Sales_Data!H9 | ... O9: =Sales_Data!O9
A10: =Sales_Data!A10 | B10: =Sales_Data!B10 | C10: =Sales_Data!C10 | D10: =Sales_Data!D10 | E10: =Sales_Data!E10 | F10: =Sales_Data!F10 | G10: =Sales_Data!G10 | H10: =Sales_Data!H10 | ... O10: =Sales_Data!O10
A11: =Sales_Data!A11 | B11: =Sales_Data!B11 | C11: =Sales_Data!C11 | D11: =Sales_Data!D11 | E11: =Sales_Data!E11 | F11: =Sales_Data!F11 | G11: =Sales_Data!G11 | H11: =Sales_Data!H11 | ... O11: =Sales_Data!O11
A12: =Sales_Data!A12 | B12: =Sales_Data!B12 | C12: =Sales_Data!C12 | D12: =Sales_Data!D12 | E12: =Sales_Data!E12 | F12: =Sales_Data!F12 | G12: =Sales_Data!G12 | H12: =Sales_Data!H12 | ... O12: =Sales_Data!O12
A13: =Sales_Data!A13 | B13: =Sales_Data!B13 | C13: =Sales_Data!C13 | D13: =Sales_Data!D13 | E13: =Sales_Data!E13 | F13: =Sales_Data!F13 | G13: =Sales_Data!G13 | H13: =Sales_Data!H13 | ... O13: =Sales_Data!O13
A14: =Sales_Data!A14 | B14: =Sales_Data!B14 | C14: =Sales_Data!C14 | D14: =Sales_Data!D14 | E14: =Sales_Data!E14 | F14: =Sales_Data!F14 | G14: =Sales_Data!G14 | H14: =Sales_Data!H14 | ... O14: =Sales_Data!O14
A15: =Sales_Data!A15 | B15: =Sales_Data!B15 | C15: =Sales_Data!C15 | D15: =Sales_Data!D15 | E15: =Sales_Data!E15 | F15: =Sales_Data!F15 | G15: =Sales_Data!G15 | H15: =Sales_Data!H15 | ... O15: =Sales_Data!O15
... A121: =Sales_Data!A121 | B121: =Sales_Data!B121 | C121: =Sales_Data!C121 | D121: =Sales_Data!D121 | E121: =Sales_Data!E121 | F121: =Sales_Data!F121 | G121: =Sales_Data!G121 | H121: =Sales_Data!H121 | ... O121: =Sales_Data!O121

Sheet T7_Cond_Format_Functions
A1: Task 7: Conditional Formatting and Excel Functions
A2: Source data: Sales_Data rows 2 to 121. Every result below is a live formula.
A4: A. Conditional formatting rules (applied on Sales_Data)
A5: Column | B5: Rule | C5: Format applied | D5: Why it is useful
A6: Profit (N) | B6: Value is less than 0 | C6: Light red fill, dark red text | D6: Spots loss-making orders at a glance.
A7: Sales (K) | B7: Value is 1,000 or more | C7: Light green fill, dark green text | D7: Highlights high-value orders.
A8: Discount (M) | B8: Value is 30% or more | C8: Light yellow fill, brown text | D8: Flags heavy discounts, which can push an order into a loss.
A9: Loss Flag (O) | B9: Text equals Loss | C9: Light red fill, dark red text | D9: Highlights rows that the IF formula labelled Loss.
A11: B. Functions: IF, COUNTIF and SUMIF
A12: Function | B12: Result | C12: What it answers | D12: Purpose of the function | E12: Check
A13: IF | B13: =IF(SUM(Sales_Data!N2:N121)>0,"Profitable overall","Loss overall") | C13: Is total profit positive? | D13: IF returns one value when a condition is TRUE and another when it is FALSE. Used here for the overall verdict and for the per-order Loss Flag in Sales_Data column O.
A14: COUNTIF | B14: =COUNTIF(Sales_Data!N2:N121,"<0") | C14: How many orders made a loss? | D14: COUNTIF counts the cells in a range that meet one condition. Used here to count negative profit values.
A15: COUNTIF | B15: =COUNTIF(Sales_Data!O2:O121,"Loss") | C15: Cross-check: how many rows are labelled Loss? | D15: Counts text matches. It should equal the result above, so the IF formulas and the COUNTIF agree. | E15: =IF(B14=B15,"Matches","Mismatch")
A16: SUMIF | B16: =SUMIF(Sales_Data!I2:I121,"Technology",Sales_Data!K2:K121) | C16: Total sales for the Technology category | D16: SUMIF adds the values in one column (Sales) only where a condition in another column (Category) is met.
A17: SUMIF | B17: =SUMIF(Sales_Data!I2:I121,"Furniture",Sales_Data!N2:N121) | C17: Total profit for the Furniture category | D17: A second SUMIF, this time adding Profit. A negative result means the category lost money overall.
A19: C. Category summary combining COUNTIF, SUMIF and IF
A20: Category | B20: Orders (COUNTIF) | C20: Total Sales (SUMIF) | D20: Total Profit (SUMIF) | E20: Status (IF)
A21: Furniture | B21: =COUNTIF(Sales_Data!$I$2:$I$121,A21) | C21: =SUMIF(Sales_Data!$I$2:$I$121,A21,Sales_Data!$K$2:$K$121) | D21: =SUMIF(Sales_Data!$I$2:$I$121,A21,Sales_Data!$N$2:$N$121) | E21: =IF(D21>=0,"Profitable","Loss-making")
A22: Office Supplies | B22: =COUNTIF(Sales_Data!$I$2:$I$121,A22) | C22: =SUMIF(Sales_Data!$I$2:$I$121,A22,Sales_Data!$K$2:$K$121) | D22: =SUMIF(Sales_Data!$I$2:$I$121,A22,Sales_Data!$N$2:$N$121) | E22: =IF(D22>=0,"Profitable","Loss-making")
A23: Technology | B23: =COUNTIF(Sales_Data!$I$2:$I$121,A23) | C23: =SUMIF(Sales_Data!$I$2:$I$121,A23,Sales_Data!$K$2:$K$121) | D23: =SUMIF(Sales_Data!$I$2:$I$121,A23,Sales_Data!$N$2:$N$121) | E23: =IF(D23>=0,"Profitable","Loss-making")
A24: Total | B24: =SUM(B21:B23) | C24: =SUM(C21:C23) | D24: =SUM(D21:D23) | E24: =IF(D24>=0,"Profitable","Loss-making")

Sheet T8_VLOOKUP_XLOOKUP
A1: Task 8: VLOOKUP and XLOOKUP
A2: Product_Master (table 2) is looked up using Product ID from Sales_Data (table 1). The two tables are related through Product ID.
A4: Part A: Retrieve product details for sample orders
A5: Order ID | B5: Product ID | C5: VLOOKUP: Product Name | D5: VLOOKUP: Unit Price | E5: XLOOKUP: Product Name | F5: XLOOKUP: Unit Price | G5: Results match?
A6: =Sales_Data!A2 | B6: =Sales_Data!H2 | C6: =IFERROR(VLOOKUP(B6,Product_Master!$A$2:$E$22,2,FALSE),"Not found") | D6: =IFERROR(VLOOKUP(B6,Product_Master!$A$2:$E$22,5,FALSE),"Not found") | E6: =_xlfn.XLOOKUP(B6,Product_Master!$A$2:$A$22,Product_Master!$B$2:$B$22,"Not found") | F6: =_xlfn.XLOOKUP(B6,Product_Master!$A$2:$A$22,Product_Master!$E$2:$E$22,"Not found") | G6: =IF(AND(C6=E6,D6=F6),"Match","Check")
A7: =Sales_Data!A3 | B7: =Sales_Data!H3 | C7: =IFERROR(VLOOKUP(B7,Product_Master!$A$2:$E$22,2,FALSE),"Not found") | D7: =IFERROR(VLOOKUP(B7,Product_Master!$A$2:$E$22,5,FALSE),"Not found") | E7: =_xlfn.XLOOKUP(B7,Product_Master!$A$2:$A$22,Product_Master!$B$2:$B$22,"Not found") | F7: =_xlfn.XLOOKUP(B7,Product_Master!$A$2:$A$22,Product_Master!$E$2:$E$22,"Not found") | G7: =IF(AND(C7=E7,D7=F7),"Match","Check")
A8: =Sales_Data!A4 | B8: =Sales_Data!H4 | C8: =IFERROR(VLOOKUP(B8,Product_Master!$A$2:$E$22,2,FALSE),"Not found") | D8: =IFERROR(VLOOKUP(B8,Product_Master!$A$2:$E$22,5,FALSE),"Not found") | E8: =_xlfn.XLOOKUP(B8,Product_Master!$A$2:$A$22,Product_Master!$B$2:$B$22,"Not found") | F8: =_xlfn.XLOOKUP(B8,Product_Master!$A$2:$A$22,Product_Master!$E$2:$E$22,"Not found") | G8: =IF(AND(C8=E8,D8=F8),"Match","Check")
A9: =Sales_Data!A5 | B9: =Sales_Data!H5 | C9: =IFERROR(VLOOKUP(B9,Product_Master!$A$2:$E$22,2,FALSE),"Not found") | D9: =IFERROR(VLOOKUP(B9,Product_Master!$A$2:$E$22,5,FALSE),"Not found") | E9: =_xlfn.XLOOKUP(B9,Product_Master!$A$2:$A$22,Product_Master!$B$2:$B$22,"Not found") | F9: =_xlfn.XLOOKUP(B9,Product_Master!$A$2:$A$22,Product_Master!$E$2:$E$22,"Not found") | G9: =IF(AND(C9=E9,D9=F9),"Match","Check")
A10: =Sales_Data!A6 | B10: =Sales_Data!H6 | C10: =IFERROR(VLOOKUP(B10,Product_Master!$A$2:$E$22,2,FALSE),"Not found") | D10: =IFERROR(VLOOKUP(B10,Product_Master!$A$2:$E$22,5,FALSE),"Not found") | E10: =_xlfn.XLOOKUP(B10,Product_Master!$A$2:$A$22,Product_Master!$B$2:$B$22,"Not found") | F10: =_xlfn.XLOOKUP(B10,Product_Master!$A$2:$A$22,Product_Master!$E$2:$E$22,"Not found") | G10: =IF(AND(C10=E10,D10=F10),"Match","Check")
A11: =Sales_Data!A7 | B11: =Sales_Data!H7 | C11: =IFERROR(VLOOKUP(B11,Product_Master!$A$2:$E$22,2,FALSE),"Not found") | D11: =IFERROR(VLOOKUP(B11,Product_Master!$A$2:$E$22,5,FALSE),"Not found") | E11: =_xlfn.XLOOKUP(B11,Product_Master!$A$2:$A$22,Product_Master!$B$2:$B$22,"Not found") | F11: =_xlfn.XLOOKUP(B11,Product_Master!$A$2:$A$22,Product_Master!$E$2:$E$22,"Not found") | G11: =IF(AND(C11=E11,D11=F11),"Match","Check")
A12: =Sales_Data!A8 | B12: =Sales_Data!H8 | C12: =IFERROR(VLOOKUP(B12,Product_Master!$A$2:$E$22,2,FALSE),"Not found") | D12: =IFERROR(VLOOKUP(B12,Product_Master!$A$2:$E$22,5,FALSE),"Not found") | E12: =_xlfn.XLOOKUP(B12,Product_Master!$A$2:$A$22,Product_Master!$B$2:$B$22,"Not found") | F12: =_xlfn.XLOOKUP(B12,Product_Master!$A$2:$A$22,Product_Master!$E$2:$E$22,"Not found") | G12: =IF(AND(C12=E12,D12=F12),"Match","Check")
A13: =Sales_Data!A9 | B13: =Sales_Data!H9 | C13: =IFERROR(VLOOKUP(B13,Product_Master!$A$2:$E$22,2,FALSE),"Not found") | D13: =IFERROR(VLOOKUP(B13,Product_Master!$A$2:$E$22,5,FALSE),"Not found") | E13: =_xlfn.XLOOKUP(B13,Product_Master!$A$2:$A$22,Product_Master!$B$2:$B$22,"Not found") | F13: =_xlfn.XLOOKUP(B13,Product_Master!$A$2:$A$22,Product_Master!$E$2:$E$22,"Not found") | G13: =IF(AND(C13=E13,D13=F13),"Match","Check")
A14: =Sales_Data!A10 | B14: =Sales_Data!H10 | C14: =IFERROR(VLOOKUP(B14,Product_Master!$A$2:$E$22,2,FALSE),"Not found") | D14: =IFERROR(VLOOKUP(B14,Product_Master!$A$2:$E$22,5,FALSE),"Not found") | E14: =_xlfn.XLOOKUP(B14,Product_Master!$A$2:$A$22,Product_Master!$B$2:$B$22,"Not found") | F14: =_xlfn.XLOOKUP(B14,Product_Master!$A$2:$A$22,Product_Master!$E$2:$E$22,"Not found") | G14: =IF(AND(C14=E14,D14=F14),"Match","Check")
A15: =Sales_Data!A11 | B15: =Sales_Data!H11 | C15: =IFERROR(VLOOKUP(B15,Product_Master!$A$2:$E$22,2,FALSE),"Not found") | D15: =IFERROR(VLOOKUP(B15,Product_Master!$A$2:$E$22,5,FALSE),"Not found") | E15: =_xlfn.XLOOKUP(B15,Product_Master!$A$2:$A$22,Product_Master!$B$2:$B$22,"Not found") | F15: =_xlfn.XLOOKUP(B15,Product_Master!$A$2:$A$22,Product_Master!$E$2:$E$22,"Not found") | G15: =IF(AND(C15=E15,D15=F15),"Match","Check")
A16: =Sales_Data!A12 | B16: =Sales_Data!H12 | C16: =IFERROR(VLOOKUP(B16,Product_Master!$A$2:$E$22,2,FALSE),"Not found") | D16: =IFERROR(VLOOKUP(B16,Product_Master!$A$2:$E$22,5,FALSE),"Not found") | E16: =_xlfn.XLOOKUP(B16,Product_Master!$A$2:$A$22,Product_Master!$B$2:$B$22,"Not found") | F16: =_xlfn.XLOOKUP(B16,Product_Master!$A$2:$A$22,Product_Master!$E$2:$E$22,"Not found") | G16: =IF(AND(C16=E16,D16=F16),"Match","Check")
A17: =Sales_Data!A13 | B17: =Sales_Data!H13 | C17: =IFERROR(VLOOKUP(B17,Product_Master!$A$2:$E$22,2,FALSE),"Not found") | D17: =IFERROR(VLOOKUP(B17,Product_Master!$A$2:$E$22,5,FALSE),"Not found") | E17: =_xlfn.XLOOKUP(B17,Product_Master!$A$2:$A$22,Product_Master!$B$2:$B$22,"Not found") | F17: =_xlfn.XLOOKUP(B17,Product_Master!$A$2:$A$22,Product_Master!$E$2:$E$22,"Not found") | G17: =IF(AND(C17=E17,D17=F17),"Match","Check")
A18: TEST-01 | B18: FAKE-999 | C18: =IFERROR(VLOOKUP(B18,Product_Master!$A$2:$E$22,2,FALSE),"Not found") | D18: =IFERROR(VLOOKUP(B18,Product_Master!$A$2:$E$22,5,FALSE),"Not found") | E18: =_xlfn.XLOOKUP(B18,Product_Master!$A$2:$A$22,Product_Master!$B$2:$B$22,"Not found") | F18: =_xlfn.XLOOKUP(B18,Product_Master!$A$2:$A$22,Product_Master!$E$2:$E$22,"Not found") | G18: =IF(AND(C18=E18,D18=F18),"Match","Check")
A19: Row 18 uses an ID that is not in Product_Master (yellow cells are inputs). Both functions return "Not found" instead of an error.
A21: Part B: Reverse lookup, finding Product ID from Product Name
A22: Product name (input): | C22: Ergonomic Mesh Chair
A24: Method | B24: Product ID returned | C24: Notes
A25: VLOOKUP | B25: Not possible | C25: VLOOKUP only returns columns to the right of the lookup column. Product ID sits to the left of Product Name, so VLOOKUP cannot return it.
A26: INDEX/MATCH | B26: =IFERROR(INDEX(Product_Master!$A$2:$A$22,MATCH($C$22,Product_Master!$B$2:$B$22,0)),"Not found") | C26: Works around the VLOOKUP limit, but needs two functions.
A27: XLOOKUP | B27: =_xlfn.XLOOKUP($C$22,Product_Master!$B$2:$B$22,Product_Master!$A$2:$A$22,"Not found") | C27: One function. It returns the column to the left directly.
A29: Part C: VLOOKUP vs XLOOKUP at a glance
A30: Feature | B30: VLOOKUP | E30: XLOOKUP
A31: Syntax | B31: VLOOKUP(lookup, table, col_index, [range_lookup]) | E31: XLOOKUP(lookup, lookup_array, return_array, [if_not_found], ...)
A32: Direction | B32: Returns only columns to the right of the key column | E32: Returns any column, to the left or to the right
A33: Column reference | B33: A column number (2, 5, ...) that breaks if columns are inserted | E33: A direct range reference, so no counting is needed
A34: Default match | B34: Approximate match if range_lookup is left out (a common source of errors) | E34: Exact match by default
A35: Missing value | B35: Shows an N/A error unless wrapped in IFERROR | E35: Built-in if_not_found argument
A36: Availability | B36: Every Excel version | E36: Excel 2021, Excel 365 and Google Sheets

Sheet T9_Pivot_Chart
A1: Task 9: Pivot Table and Chart
A2: Source: Sales_Data. Tables below use SUMIFS and SUMIF formulas, so they update when the data changes.
A4: Table 1: Sales by Category and Region (pivot-style summary)
A5: Category | B5: Central | C5: East | D5: North | E5: South | F5: West | G5: Grand Total
A6: Furniture | B6: =SUMIFS(Sales_Data!$K$2:$K$121,Sales_Data!$I$2:$I$121,$A6,Sales_Data!$G$2:$G$121,B$5) | C6: =SUMIFS(Sales_Data!$K$2:$K$121,Sales_Data!$I$2:$I$121,$A6,Sales_Data!$G$2:$G$121,C$5) | D6: =SUMIFS(Sales_Data!$K$2:$K$121,Sales_Data!$I$2:$I$121,$A6,Sales_Data!$G$2:$G$121,D$5) | E6: =SUMIFS(Sales_Data!$K$2:$K$121,Sales_Data!$I$2:$I$121,$A6,Sales_Data!$G$2:$G$121,E$5) | F6: =SUMIFS(Sales_Data!$K$2:$K$121,Sales_Data!$I$2:$I$121,$A6,Sales_Data!$G$2:$G$121,F$5) | G6: =SUM(B6:F6)
A7: Office Supplies | B7: =SUMIFS(Sales_Data!$K$2:$K$121,Sales_Data!$I$2:$I$121,$A7,Sales_Data!$G$2:$G$121,B$5) | C7: =SUMIFS(Sales_Data!$K$2:$K$121,Sales_Data!$I$2:$I$121,$A7,Sales_Data!$G$2:$G$121,C$5) | D7: =SUMIFS(Sales_Data!$K$2:$K$121,Sales_Data!$I$2:$I$121,$A7,Sales_Data!$G$2:$G$121,D$5) | E7: =SUMIFS(Sales_Data!$K$2:$K$121,Sales_Data!$I$2:$I$121,$A7,Sales_Data!$G$2:$G$121,E$5) | F7: =SUMIFS(Sales_Data!$K$2:$K$121,Sales_Data!$I$2:$I$121,$A7,Sales_Data!$G$2:$G$121,F$5) | G7: =SUM(B7:F7)
A8: Technology | B8: =SUMIFS(Sales_Data!$K$2:$K$121,Sales_Data!$I$2:$I$121,$A8,Sales_Data!$G$2:$G$121,B$5) | C8: =SUMIFS(Sales_Data!$K$2:$K$121,Sales_Data!$I$2:$I$121,$A8,Sales_Data!$G$2:$G$121,C$5) | D8: =SUMIFS(Sales_Data!$K$2:$K$121,Sales_Data!$I$2:$I$121,$A8,Sales_Data!$G$2:$G$121,D$5) | E8: =SUMIFS(Sales_Data!$K$2:$K$121,Sales_Data!$I$2:$I$121,$A8,Sales_Data!$G$2:$G$121,E$5) | F8: =SUMIFS(Sales_Data!$K$2:$K$121,Sales_Data!$I$2:$I$121,$A8,Sales_Data!$G$2:$G$121,F$5) | G8: =SUM(B8:F8)
A9: Grand Total | B9: =SUM(B6:B8) | C9: =SUM(C6:C8) | D9: =SUM(D6:D8) | E9: =SUM(E6:E8) | F9: =SUM(F6:F8) | G9: =SUM(G6:G8)
A11: Table 2: Sales, profit and profit margin by Category
A12: Category | B12: Total Sales | C12: Total Profit | D12: Profit Margin
A13: Furniture | B13: =SUMIF(Sales_Data!$I$2:$I$121,A13,Sales_Data!$K$2:$K$121) | C13: =SUMIF(Sales_Data!$I$2:$I$121,A13,Sales_Data!$N$2:$N$121) | D13: =IF(B13=0,0,C13/B13)
A14: Office Supplies | B14: =SUMIF(Sales_Data!$I$2:$I$121,A14,Sales_Data!$K$2:$K$121) | C14: =SUMIF(Sales_Data!$I$2:$I$121,A14,Sales_Data!$N$2:$N$121) | D14: =IF(B14=0,0,C14/B14)
A15: Technology | B15: =SUMIF(Sales_Data!$I$2:$I$121,A15,Sales_Data!$K$2:$K$121) | C15: =SUMIF(Sales_Data!$I$2:$I$121,A15,Sales_Data!$N$2:$N$121) | D15: =IF(B15=0,0,C15/B15)
A16: Total | B16: =SUM(B13:B15) | C16: =SUM(C13:C15) | D16: =IF(B16=0,0,C16/B16)
A18: Chart explanation
A19: The clustered column chart compares sales for each category across the five regions. Technology has the largest bars in Central, East and West, with Central the highest at about $21,109. Furniture leads in North and South, and its biggest region is West at about $9,074. Office Supplies is the smallest category in every region. The chart measures sales volume only. Table 2 shows that Furniture lost money overall (margin about -1.3%), while Office Supplies earned about 14.4% and Technology about 8.5%. In dollar terms Technology is also the most profitable category, but its margin is below Office Supplies, and Furniture loses money overall even though it leads sales in North and South.
A21: How to make a native PivotTable in Excel (optional, takes about one minute)
A22: Click any cell in Sales_Data, then go to Insert > PivotTable and choose OK. Drag Category into Rows, Region into Columns, and Sales into Values (Sum). Table 1 above shows the same figures.

Sheet Product_Master
A1: Product ID | B1: Product Name | C1: Category | D1: Sub-Category | E1: Unit Price
A2: FUR-CH-01 | B2: Executive Leather Armchair | C2: Furniture | D2: Chairs | E2: 645
A3: FUR-CH-02 | B3: Ergonomic Mesh Chair | C3: Furniture | D3: Chairs | E3: 389.99
A4: FUR-CH-03 | B4: Stackable Guest Chair | C4: Furniture | D4: Chairs | E4: 129.5
A5: FUR-TB-01 | B5: Conference Table 8-Seater | C5: Furniture | D5: Tables | E5: 1180
A6: FUR-TB-02 | B6: Adjustable Standing Desk | C6: Furniture | D6: Tables | E6: 520
A7: FUR-BK-01 | B7: Five-Shelf Bookcase | C7: Furniture | D7: Bookcases | E7: 210
A8: FUR-BK-02 | B8: Glass-Door Cabinet | C8: Furniture | D8: Bookcases | E8: 365
A9: FUR-FN-01 | B9: Desk Lamp with Clamp | C9: Furniture | D9: Furnishings | E9: 48.75
A10: FUR-FN-02 | B10: Wall Clock 12-inch | C10: Furniture | D10: Furnishings | E10: 24.99
A11: OFS-BI-01 | B11: Heavy-Duty Ring Binder | C11: Office Supplies | D11: Binders | E11: 11.4
A12: OFS-BI-02 | B12: Clear Presentation Binder | C12: Office Supplies | D12: Binders | E12: 6.85
A13: OFS-PA-01 | B13: Copier Paper A4 (Ream) | C13: Office Supplies | D13: Paper | E13: 9.6
... A22: TEC-MA-01 | B22: Multifunction Laser Printer | C22: Technology | D22: Machines | E22: 899
A24: Note: Unit Price is the list price per unit (sample values set for this workbook). Product ID in column A is the lookup key used by VLOOKUP and XLOOKUP on T8.
